README
setup.py
apihangar/__init__.py
apihangar/admin.py
apihangar/core.py
apihangar/models.py
apihangar/registry.py
apihangar/required_settings.py
apihangar/urls.py
apihangar/utils.py
apihangar/views.py
django_apihangar.egg-info/PKG-INFO
django_apihangar.egg-info/SOURCES.txt
django_apihangar.egg-info/dependency_links.txt
django_apihangar.egg-info/entry_points.txt
django_apihangar.egg-info/not-zip-safe
django_apihangar.egg-info/requires.txt
django_apihangar.egg-info/top_level.txt