Metadata-Version: 1.0
Name: django-apihangar
Version: 0.1.1
Summary: through-the-web creation of templated sql->json APIs for querying data
Home-page: UNKNOWN
Author: Ethan Jucovy
Author-email: ethan@boldprogressives.org
License: BSD
Platform: UNKNOWN
Classifier: Development Status :: 4 - Beta
Classifier: Framework :: Django
Classifier: License :: OSI Approved :: BSD License
